easysqlite/__init__.py
easysqlite/easysqlite.py
easysqlite-0.1.1.dist-info/METADATA
easysqlite-0.1.1.dist-info/WHEEL
easysqlite-0.1.1.dist-info/top_level.txt
easysqlite-0.1.1.dist-info/RECORD
