Metadata-Version: 2.1
Name: easysqlite
Version: 0.1.1
Summary: Wrapper librray for SQLite3
Home-page: https://github.com/PowerBroker2/easysqlite
Author: Power_Broker
Author-email: gitstuff2@gmail.com
License: UNKNOWN
Download-URL: https://github.com/PowerBroker2/easysqlite/archive/0.1.1.tar.gz
Keywords: SQL,sqlite3,sqlite
Platform: UNKNOWN
Requires-Dist: sqlite3
